{
  "allGdId": [
    {
      "gdId": "",
      "id": 1
    },
    {
      "gdId": "GD34533",
      "id": 2
    },
    {
      "gdId": "GD12345",
      "id": 3
    },
    {
      "gdId": "GD46703",
      "id": 4
    },
    {
      "gdId": "GD20240",
      "id": 5
    },
    {
      "gdId": "GD39109",
      "id": 6
    },
    {
      "gdId": "GD21589",
      "id": 7
    },
    {
      "gdId": "GD47951",
      "id": 8
    },
    {
      "gdId": "GD19807",
      "id": 9
    },
    {
      "gdId": "GD30127",
      "id": 10
    },
    {
      "gdId": "GD80711",
      "id": 11
    },
    {
      "gdId": "GD47224",
      "id": 12
    },
    {
      "gdId": "GD12607",
      "id": 13
    },
    {
      "gdId": "GD18530",
      "id": 14
    },
    {
      "gdId": "GD93380",
      "id": 15
    },
    {
      "gdId": "GD84188",
      "id": 16
    }
  ]
}